configs/mainnet.yaml
configs/minimal.yaml
eth2spec/VERSION.txt
eth2spec/__init__.py
eth2spec/altair/__init__.py
eth2spec/altair/mainnet.py
eth2spec/altair/minimal.py
eth2spec/bellatrix/__init__.py
eth2spec/bellatrix/mainnet.py
eth2spec/bellatrix/minimal.py
eth2spec/capella/__init__.py
eth2spec/capella/mainnet.py
eth2spec/capella/minimal.py
eth2spec/config/__init__.py
eth2spec/config/config_util.py
eth2spec/debug/__init__.py
eth2spec/debug/decode.py
eth2spec/debug/encode.py
eth2spec/debug/random_value.py
eth2spec/gen_helpers/__init__.py
eth2spec/gen_helpers/gen_base/__init__.py
eth2spec/gen_helpers/gen_base/gen_runner.py
eth2spec/gen_helpers/gen_base/gen_typing.py
eth2spec/gen_helpers/gen_from_tests/__init__.py
eth2spec/gen_helpers/gen_from_tests/gen.py
eth2spec/merge/__init__.py
eth2spec/merge/mainnet.py
eth2spec/merge/minimal.py
eth2spec/phase0/__init__.py
eth2spec/phase0/mainnet.py
eth2spec/phase0/minimal.py
eth2spec/test/__init__.py
eth2spec/test/conftest.py
eth2spec/test/context.py
eth2spec/test/exceptions.py
eth2spec/test/altair/__init__.py
eth2spec/test/altair/block_processing/__init__.py
eth2spec/test/altair/block_processing/sync_aggregate/__init__.py
eth2spec/test/altair/block_processing/sync_aggregate/test_process_sync_aggregate.py
eth2spec/test/altair/block_processing/sync_aggregate/test_process_sync_aggregate_random.py
eth2spec/test/altair/epoch_processing/__init__.py
eth2spec/test/altair/epoch_processing/test_process_inactivity_updates.py
eth2spec/test/altair/epoch_processing/test_process_participation_flag_updates.py
eth2spec/test/altair/epoch_processing/test_process_sync_committee_updates.py
eth2spec/test/altair/fork/__init__.py
eth2spec/test/altair/fork/test_altair_fork_basic.py
eth2spec/test/altair/fork/test_altair_fork_random.py
eth2spec/test/altair/merkle/__init__.py
eth2spec/test/altair/merkle/test_single_proof.py
eth2spec/test/altair/random/__init__.py
eth2spec/test/altair/random/test_random.py
eth2spec/test/altair/sanity/__init__.py
eth2spec-1.1.10.dist-info/LICENSE
eth2spec-1.1.10.dist-info/METADATA
eth2spec-1.1.10.dist-info/WHEEL
eth2spec-1.1.10.dist-info/top_level.txt
eth2spec-1.1.10.dist-info/RECORD
