Metadata-Version: 2.1
Name: eth2spec
Version: 1.1.10
Summary: Eth2 spec, provided as Python package for tooling and testing
Home-page: https://github.com/ethereum/eth2.0-specs
Author: ethereum
License: UNKNOWN
Platform: UNKNOWN
Requires-Python: >=3.8, <4
Requires-Dist: eth-utils (<2,>=1.3.0)
Requires-Dist: eth-typing (<3.0.0,>=2.1.0)
Requires-Dist: pycryptodome (==3.9.4)
Requires-Dist: py-ecc (==5.2.0)
Requires-Dist: milagro-bls-binding (==1.6.3)
Requires-Dist: dataclasses (==0.6)
Requires-Dist: remerkleable (==0.1.24)
Requires-Dist: ruamel.yaml (==0.16.5)
Requires-Dist: lru-dict (==1.1.6)
Requires-Dist: marko (==1.0.2)
Provides-Extra: generator
Requires-Dist: python-snappy (==0.5.4) ; extra == 'generator'
Provides-Extra: lint
Requires-Dist: flake8 (==3.7.7) ; extra == 'lint'
Requires-Dist: mypy (==0.812) ; extra == 'lint'
Requires-Dist: pylint (==2.12.2) ; extra == 'lint'
Provides-Extra: test
Requires-Dist: pytest (>=4.4) ; extra == 'test'
Requires-Dist: pytest-cov ; extra == 'test'
Requires-Dist: pytest-xdist ; extra == 'test'
